uniproxy/__init__.py
uniproxy/linux_proxy.py
uniproxy/mac_proxy.py
uniproxy/shell_env_var.py
uniproxy/win_proxy.py
uniproxy-1.5.0.dist-info/LICENSE
uniproxy-1.5.0.dist-info/METADATA
uniproxy-1.5.0.dist-info/WHEEL
uniproxy-1.5.0.dist-info/RECORD
