Metadata-Version: 2.3
Name: Uniproxy
Version: 1.5.0
Summary: Cross platform python library to set system-wide proxy and bypass domains for proxy.
License: LGPL-2.0-or-later
Keywords: proxy,system-wide,cross-platform,bypass domains
Author: kun-codes
Author-email: 77796630+throwaway69420-69420@users.noreply.github.com
Requires-Python: >=3.8,<4.0
Classifier: License :: OSI Approved :: GNU Lesser General Public License v2 or later (LGPLv2+)
Classifier: Programming Language :: Python :: 3
Classifier: Programming Language :: Python :: 3.8
Classifier: Programming Language :: Python :: 3.9
Classifier: Programming Language :: Python :: 3.10
Classifier: Programming Language :: Python :: 3.11
Classifier: Programming Language :: Python :: 3.12
Classifier: Programming Language :: Python :: 3.13
Classifier: Topic :: Internet :: Proxy Servers
Classifier: Topic :: Software Development :: Libraries
Classifier: Topic :: System :: Networking
Requires-Dist: xdg (>=6.0.0,<7.0.0)
Project-URL: Repository, https://github.com/kun-codes/Uniproxy
